flow/__init__.py
flow/flow.py
flowdag-0.1.1.dist-info/LICENSE
flowdag-0.1.1.dist-info/METADATA
flowdag-0.1.1.dist-info/WHEEL
flowdag-0.1.1.dist-info/top_level.txt
flowdag-0.1.1.dist-info/RECORD
