Metadata-Version: 2.1
Name: flowdag
Version: 0.1.1
Summary: A library for processing and visualizing data
Home-page: https://github.com/renedoz/flow
Author: Marco Renedo
Classifier: Programming Language :: Python :: 3
Classifier: License :: OSI Approved :: MIT License
Classifier: Operating System :: OS Independent
Requires-Python: >=3.6
License-File: LICENSE
Requires-Dist: pandas
Requires-Dist: numpy
Requires-Dist: matplotlib
Requires-Dist: ipywidgets
Requires-Dist: autopep8
Requires-Dist: pydot
Requires-Dist: IPython
